MANIFEST.in
README.txt
setup.cfg
setup.py
docs/CHANGES.txt
docs/CONTRIBUTORS.txt
docs/HISTORY.txt
docs/INSTALL.txt
docs/LICENSE.txt
jalon/.DS_Store
jalon/__init__.py
jalon.content.egg-info/PKG-INFO
jalon.content.egg-info/SOURCES.txt
jalon.content.egg-info/dependency_links.txt
jalon.content.egg-info/entry_points.txt
jalon.content.egg-info/namespace_packages.txt
jalon.content.egg-info/not-zip-safe
jalon.content.egg-info/paster_plugins.txt
jalon.content.egg-info/requires.txt
jalon.content.egg-info/top_level.txt
jalon/content/.DS_Store
jalon/content/README.txt
jalon/content/__init__.py
jalon/content/config.py
jalon/content/configure.zcml
jalon/content/setuphandlers.py
jalon/content/skins.zcml
jalon/content/browser/.DS_Store
jalon/content/browser/__init__.py
jalon/content/browser/configure.zcml
jalon/content/browser/interfaces.py
jalon/content/browser/scripts/.DS_Store
jalon/content/browser/scripts/__init__.py
jalon/content/browser/scripts/analytics.py
jalon/content/browser/scripts/first_page.py
jalon/content/browser/scripts/indicateurs_view.py
jalon/content/browser/scripts/podcasts.py
jalon/content/browser/templates/.DS_Store
jalon/content/browser/templates/analytics.pt
jalon/content/browser/templates/cours_indicateurs_view.pt
jalon/content/browser/templates/cours_rss_view.pt
jalon/content/browser/templates/cours_wims_view.pt
jalon/content/browser/templates/exercicewims_view.pt
jalon/content/browser/templates/exercicewims_view_CORS.pt
jalon/content/browser/templates/first_page.pt
jalon/content/browser/templates/jalon_folder.pt
jalon/content/browser/templates/ressource_view.pt
jalon/content/browser/view_script/__init__.py
jalon/content/browser/view_script/course_add_view.py
jalon/content/browser/view_script/course_statistics_view.py
jalon/content/browser/view_script/course_view.py
jalon/content/browser/view_script/deposit_box_criteria_view.py
jalon/content/browser/view_script/deposit_box_evaluation_view.py
jalon/content/browser/view_script/deposit_box_view.py
jalon/content/browser/view_script/my_adobe_connect_recording_view.py
jalon/content/browser/view_script/my_courses_view.py
jalon/content/browser/view_script/my_deposit_file_view.py
jalon/content/browser/view_script/my_external_resources_view.py
jalon/content/browser/view_script/my_files_view.py
jalon/content/browser/view_script/my_glossary_terms_view.py
