Metadata-Version: 1.1
Name: jalon.content
Version: 3.1.5
Summary: UNKNOWN
Home-page: http://unice.fr
Author: Bordonado Christophe, Jerome Navarro, Olivier Bado - Université Nice Sophia Antipolis (uns) Service TICE / Jean Bado - Université Versaille Saint-Quentin(UVSQ)
Author-email: tice@unice.fr
License: CECILL
Platform: UNKNOWN
Classifier: Framework :: Plone
Classifier: Intended Audience :: Developers
Classifier: License :: OSI Approved :: GNU General Public License (GPL)
